{
  "usuarios": [
    {
      "id": 1,
      "nome": "Gisely",
      "sobrenome": "Cavalli",
      "email": "giselycavalli@xp.com",
      "senha": "123456",
      "conta": 10000.00,
      "minhasAcoes": [
        {
          "id": 1,
          "nomeAcao": "AZUL4",
          "preco": "350,00",
          "quantidade": 100
        },
        {
          "id": 3,
          "nomeAcao": "VALE4",
          "preco": "350,00",
          "quantidade": 100
        },
        {
          "id": 8,
          "nomeAcao": "MGLU3",
          "preco": "350,00",
          "quantidade": 100
        }
      ]
    },
    {
      "id": 1,
      "nome": "Leandro",
      "sobrenome": "Benedito",
      "email": "leandrobenedito@xp.com",
      "senha": "123456",
      "conta": 1000.00,
      "minhasAcoes": [
        {
          "id": 8,
          "nomeAcao": "MGLU3",
          "preco": "350,00",
          "quantidade": 100
        },
        {
          "id": 5,
          "nomeAcao": "ABEV3",
          "preco": "350,00",
          "quantidade": 100
        }
      ]
    }
  ],
  "acoes": [
    {
      "id": 1,
      "nomeAcao": "AZUL4",
      "preco": "350,00",
      "quantidade": 1
    },
    {
      "id": 2,
      "nomeAcao": "PETR4",
      "preco": "350,00",
      "quantidade": 1
    },
    {
      "id": 3,
      "nomeAcao": "VALE4",
      "preco": "350,00",
      "quantidade": 1
    },
    {
      "id": 4,
      "nomeAcao": "ITUB4",
      "preco": "350,00",
      "quantidade": 1
    },
    {
      "id": 5,
      "nomeAcao": "ABEV3",
      "preco": "350,00",
      "quantidade": 1
    },
    {
      "id": 6,
      "nomeAcao": "GOLL4",
      "preco": "350,00",
      "quantidade": 1
    },
    {
      "id": 7,
      "nomeAcao": "EMBR3",
      "preco": "350,00",
      "quantidade": 1
    },
    {
      "id": 8,
      "nomeAcao": "MGLU3",
      "preco": "350,00",
      "quantidade": 1
    }
    
  ]
}